lib/libdependencies.so
pynusmv/__init__.py
pynusmv/collections.py
pynusmv/dd.py
pynusmv/exception.py
pynusmv/fsm.py
pynusmv/glob.py
pynusmv/init.py
pynusmv/mc.py
pynusmv/model.py
pynusmv/node.py
pynusmv/parser.py
pynusmv/prop.py
pynusmv/sat.py
pynusmv/trace.py
pynusmv/utils.py
pynusmv/wff.py
pynusmv/be/__init__.py
pynusmv/be/encoder.py
pynusmv/be/expression.py
pynusmv/be/fsm.py
pynusmv/be/manager.py
pynusmv/bmc/__init__.py
pynusmv/bmc/glob.py
pynusmv/bmc/invarspec.py
pynusmv/bmc/ltlspec.py
pynusmv/bmc/utils.py
pynusmv/sexp/__init__.py
pynusmv/sexp/fsm.py
pynusmv-1.0rc8.dist-info/DESCRIPTION.rst
pynusmv-1.0rc8.dist-info/METADATA
pynusmv-1.0rc8.dist-info/RECORD
pynusmv-1.0rc8.dist-info/WHEEL
pynusmv-1.0rc8.dist-info/metadata.json
pynusmv-1.0rc8.dist-info/top_level.txt
pynusmv_lower_interface/__init__.py
pynusmv_lower_interface/bmc_utils/__init__.py
pynusmv_lower_interface/bmc_utils/_bmc_utils.cpython-36m-darwin.so
pynusmv_lower_interface/bmc_utils/bmc_utils.py
pynusmv_lower_interface/nusmv/__init__.py
pynusmv_lower_interface/nusmv/addons_core/__init__.py
pynusmv_lower_interface/nusmv/addons_core/_addons_core.cpython-36m-darwin.so
pynusmv_lower_interface/nusmv/addons_core/addons_core.py
pynusmv_lower_interface/nusmv/addons_core/compass/__init__.py
pynusmv_lower_interface/nusmv/addons_core/compass/_compass.cpython-36m-darwin.so
pynusmv_lower_interface/nusmv/addons_core/compass/compass.py
pynusmv_lower_interface/nusmv/addons_core/compass/compile/__init__.py
pynusmv_lower_interface/nusmv/addons_core/compass/compile/_compile.cpython-36m-darwin.so
pynusmv_lower_interface/nusmv/addons_core/compass/compile/compile.py
pynusmv_lower_interface/nusmv/addons_core/compass/parser/__init__.py
pynusmv_lower_interface/nusmv/addons_core/compass/parser/ap/__init__.py
pynusmv_lower_interface/nusmv/addons_core/compass/parser/ap/_ap.cpython-36m-darwin.so
pynusmv_lower_interface/nusmv/addons_core/compass/parser/ap/ap.py
pynusmv_lower_interface/nusmv/addons_core/compass/parser/prob/__init__.py
pynusmv_lower_interface/nusmv/addons_core/compass/parser/prob/_prob.cpython-36m-darwin.so
pynusmv_lower_interface/nusmv/addons_core/compass/parser/prob/prob.py
